{"Gz+M5m8R1lZAG0Z0zr8vgQ==":"logo-128x128.png","zOsztEXvaVIsbFdk06VsLA==":"1-2000x833.jpg","V30WPRKDFcOTUeREOI8XJg==":"2-2000x833.jpg","5MAqpJBDjlTsRUxIli6Qgg==":"4-2000x833.jpg","y1Bgb1Ulc5QH6qXAXLkMOA==":"img-600x400.jpg","clw/FP6Q4wNfNEjVQ4pImw==":"img-1-600x400.jpg","iSXHV5TFzuYP4fl77nhz6g==":"img-2-600x400.jpg","neM1nuUKaV5MRZzgj3VcvQ==":"img-1400x933.jpg","1KIgwukmg+AMvpxnll8r5Q==":"2-1400x583.jpg","S9T+ktjSAsNxu6R++swa6w==":"img-2000x1333.jpg","KENgXUtTnyuCDGjd2qm/xg==":"img-1-1400x933.jpg"}